{
  "meta": {
    "last_updated": 1769353374703,
    "strategy": "prefix-grouped",
    "version": 2
  },
  "index": {
    "d": [
      {
        "id": "kw_e603f7e8-fac9-4e42-8d0a-2eb2c54c673d",
        "keyword": "Denny Caknan - Tunggal Eka ...",
        "tags": [],
        "weight": 1,
        "impressions": 1,
        "clicks": 0,
        "last_search": 1769347120289,
        "created_at": 1769347120288,
        "locale": "id"
      },
      {
        "id": "kw_fc6e7e99-a06d-41f8-a1af-ed296f404719",
        "keyword": "Denny Caknan - Wirang",
        "tags": [],
        "weight": 1,
        "impressions": 5,
        "clicks": 0,
        "last_search": 1769349381266,
        "created_at": 1769347230918,
        "locale": "id"
      },
      {
        "id": "kw_659450bb-0152-461d-90a5-fe7baaddfc0b",
        "keyword": "Denny Caknan - Cundamani ...",
        "tags": [],
        "weight": 1,
        "impressions": 2,
        "clicks": 0,
        "last_search": 1769349381265,
        "created_at": 1769348962015,
        "locale": "id"
      },
      {
        "id": "kw_27d30b70-0316-4ef4-aa20-6eb9136a7eef",
        "keyword": "Denny Caknan - Langgeng Dayaning Rasa (LDR ...",
        "tags": [],
        "weight": 1,
        "impressions": 2,
        "clicks": 0,
        "last_search": 1769349381265,
        "created_at": 1769348962016,
        "locale": "id"
      },
      {
        "id": "kw_b8cec38a-142d-4ab8-989b-15a670d8091d",
        "keyword": "Denny Caknan - Sigar",
        "tags": [],
        "weight": 1,
        "impressions": 2,
        "clicks": 0,
        "last_search": 1769349381266,
        "created_at": 1769348962016,
        "locale": "id"
      },
      {
        "id": "kw_3ca68c4d-face-4da7-8758-7d9237d42c7e",
        "keyword": "Denny Caknan - Kalih Welasku ...",
        "tags": [],
        "weight": 1,
        "impressions": 2,
        "clicks": 0,
        "last_search": 1769349381266,
        "created_at": 1769348962016,
        "locale": "id"
      },
      {
        "id": "kw_7c6537e6-90e1-4ae5-a1fb-bd2581fecbf7",
        "keyword": "Denny Caknan - Sugeng Dalu ...",
        "tags": [],
        "weight": 1,
        "impressions": 2,
        "clicks": 0,
        "last_search": 1769349381266,
        "created_at": 1769348962016,
        "locale": "id"
      },
      {
        "id": "kw_92122421-5a12-4501-8dda-52ad722554fe",
        "keyword": "Denny Caknan",
        "tags": [],
        "weight": 1,
        "impressions": 1,
        "clicks": 0,
        "last_search": 1769349381265,
        "created_at": 1769349381265,
        "locale": "id"
      }
    ],
    "k": [
      {
        "id": "kw_631e4674-02b7-4969-9570-543a5b2a0f78",
        "keyword": "Kumpulan Gitar Denny Caknan",
        "tags": [],
        "weight": 1,
        "impressions": 3,
        "clicks": 0,
        "last_search": 1769349381265,
        "created_at": 1769347120289,
        "locale": "id"
      },
      {
        "id": "kw_4120fb76-71f1-4426-a3e6-ceb4891add3f",
        "keyword": "Kalih Welasku ...",
        "tags": [],
        "weight": 1,
        "impressions": 1,
        "clicks": 0,
        "last_search": 1769349381266,
        "created_at": 1769349381266,
        "locale": "id"
      }
    ],
    "p": [
      {
        "id": "kw_b29f6127-ee3f-4867-83fe-bd480cb0d1d8",
        "keyword": "Pujiono - Manisnya Negeriku",
        "tags": [],
        "weight": 1,
        "impressions": 1,
        "clicks": 0,
        "last_search": 1769347120290,
        "created_at": 1769347120290,
        "locale": "id"
      },
      {
        "id": "kw_e8ba87a2-d550-4194-96ec-08d134708f61",
        "keyword": "Pakdhe Baz - AJRIH",
        "tags": [],
        "weight": 1,
        "impressions": 3,
        "clicks": 0,
        "last_search": 1769353374702,
        "created_at": 1769348962016,
        "locale": "id"
      },
      {
        "id": "kw_1e761075-38eb-42c5-b211-461e827c97fb",
        "keyword": "Pakdhe Baz",
        "tags": [],
        "weight": 1,
        "impressions": 2,
        "clicks": 0,
        "last_search": 1769353374702,
        "created_at": 1769349381265,
        "locale": "id"
      },
      {
        "id": "kw_e1ceeaed-da03-420c-9448-e03311225afe",
        "keyword": "Prei Sayang ...",
        "tags": [],
        "weight": 1,
        "impressions": 1,
        "clicks": 0,
        "last_search": 1769353374702,
        "created_at": 1769353374702,
        "locale": "id"
      }
    ],
    "r": [
      {
        "id": "kw_0c98969a-5d0e-412e-8f72-6fcd136971a5",
        "keyword": "Rhoma Irama - 135 Juta",
        "tags": [],
        "weight": 1,
        "impressions": 1,
        "clicks": 0,
        "last_search": 1769347120290,
        "created_at": 1769347120290,
        "locale": "id"
      },
      {
        "id": "kw_684937cf-1ff1-4296-813d-2e857d0c6de2",
        "keyword": "Rasah Bali - LAVORA Ft Ena Vika ...",
        "tags": [],
        "weight": 1,
        "impressions": 2,
        "clicks": 0,
        "last_search": 1769349381266,
        "created_at": 1769348962016,
        "locale": "id"
      },
      {
        "id": "kw_894b1b24-70c4-4c96-9df0-5afeeb67e986",
        "keyword": "Rasah Bali",
        "tags": [],
        "weight": 1,
        "impressions": 1,
        "clicks": 0,
        "last_search": 1769349381266,
        "created_at": 1769349381266,
        "locale": "id"
      }
    ],
    "m": [
      {
        "id": "kw_e0f64dd3-bdd3-4980-86ae-ff887388e146",
        "keyword": "Mars Madrasah ...",
        "tags": [],
        "weight": 1,
        "impressions": 1,
        "clicks": 0,
        "last_search": 1769347120290,
        "created_at": 1769347120290,
        "locale": "id"
      },
      {
        "id": "kw_aa997873-77b1-4ccb-bc93-5e86544e84af",
        "keyword": "Marjinal - Jaga Sara (Suku, Agama, Ras Dan Antar ...",
        "tags": [],
        "weight": 1,
        "impressions": 1,
        "clicks": 0,
        "last_search": 1769347120291,
        "created_at": 1769347120291,
        "locale": "id"
      },
      {
        "id": "kw_f1c4d3cc-8dd8-4d92-8036-0fb440c27076",
        "keyword": "Maharani - Selire Welas ...",
        "tags": [],
        "weight": 1,
        "impressions": 3,
        "clicks": 0,
        "last_search": 1769347436410,
        "created_at": 1769347230920,
        "locale": "id"
      }
    ],
    "s": [
      {
        "id": "kw_51e3f4c4-0e29-4a0d-a161-92daad82fb12",
        "keyword": "Stand Here Alone - Satu indonesia ...",
        "tags": [],
        "weight": 1,
        "impressions": 1,
        "clicks": 0,
        "last_search": 1769347120290,
        "created_at": 1769347120290,
        "locale": "id"
      },
      {
        "id": "kw_5f275d9a-cde1-4dd5-aafd-e52e51c63454",
        "keyword": "Shaggydog - Jangan Gontok Gontokan ...",
        "tags": [],
        "weight": 1,
        "impressions": 1,
        "clicks": 0,
        "last_search": 1769347120291,
        "created_at": 1769347120291,
        "locale": "id"
      },
      {
        "id": "kw_0ab93487-5d46-4d9e-a256-11ad834ac506",
        "keyword": "Sultan Trenggono - Dagang Pindang ...",
        "tags": [],
        "weight": 1,
        "impressions": 3,
        "clicks": 0,
        "last_search": 1769347436410,
        "created_at": 1769347230919,
        "locale": "id"
      },
      {
        "id": "kw_bf29d5df-4125-4db1-b44c-ee0f3472059c",
        "keyword": "Sigar",
        "tags": [],
        "weight": 1,
        "impressions": 1,
        "clicks": 0,
        "last_search": 1769349381266,
        "created_at": 1769349381266,
        "locale": "id"
      },
      {
        "id": "kw_762a4143-2103-4868-a9da-e0463a5c5bf9",
        "keyword": "Sugeng Dalu ...",
        "tags": [],
        "weight": 1,
        "impressions": 1,
        "clicks": 0,
        "last_search": 1769349381266,
        "created_at": 1769349381266,
        "locale": "id"
      },
      {
        "id": "kw_e0e8c6b4-d74b-4eb2-b6d8-75a34e279461",
        "keyword": "Syahiba Saufa - Nyeliwah",
        "tags": [],
        "weight": 1,
        "impressions": 1,
        "clicks": 0,
        "last_search": 1769353374702,
        "created_at": 1769353374702,
        "locale": "id"
      },
      {
        "id": "kw_4a3ab547-1587-460f-b44c-6d658e2a0bbf",
        "keyword": "Syahiba Saufa",
        "tags": [],
        "weight": 1,
        "impressions": 1,
        "clicks": 0,
        "last_search": 1769353374702,
        "created_at": 1769353374702,
        "locale": "id"
      }
    ],
    "c": [
      {
        "id": "kw_9157bd89-97c1-4dcd-ac49-fb75dfb2526b",
        "keyword": "Cokelat - Anak Garuda",
        "tags": [],
        "weight": 1,
        "impressions": 1,
        "clicks": 0,
        "last_search": 1769347120290,
        "created_at": 1769347120290,
        "locale": "id"
      },
      {
        "id": "kw_7c7dc4eb-0ec4-4b34-b8f7-952436714985",
        "keyword": "Cundamani ...",
        "tags": [],
        "weight": 1,
        "impressions": 1,
        "clicks": 0,
        "last_search": 1769349381265,
        "created_at": 1769349381265,
        "locale": "id"
      },
      {
        "id": "kw_a13c5ea1-e0d6-46c6-92fe-cb90e8ca0968",
        "keyword": "Cikirikici Cinta ...",
        "tags": [],
        "weight": 1,
        "impressions": 1,
        "clicks": 0,
        "last_search": 1769353374701,
        "created_at": 1769353374701,
        "locale": "id"
      }
    ],
    "a": [
      {
        "id": "kw_dd281dbf-5d04-45ac-808a-0f6813c8a179",
        "keyword": "Arinaga Family - Semangat Merdeka ...",
        "tags": [],
        "weight": 1,
        "impressions": 1,
        "clicks": 0,
        "last_search": 1769347120291,
        "created_at": 1769347120291,
        "locale": "id"
      },
      {
        "id": "kw_00641d89-bef2-49fd-b7f6-bb34b3e30225",
        "keyword": "AJRIH",
        "tags": [],
        "weight": 1,
        "impressions": 2,
        "clicks": 0,
        "last_search": 1769353374702,
        "created_at": 1769349381265,
        "locale": "id"
      },
      {
        "id": "kw_a8c82d44-f882-41dd-bf8f-d907bfe359a5",
        "keyword": "Arrijal - Nemen",
        "tags": [],
        "weight": 1,
        "impressions": 1,
        "clicks": 0,
        "last_search": 1769353374702,
        "created_at": 1769353374702,
        "locale": "id"
      },
      {
        "id": "kw_17c256b5-96e7-4747-a51b-b74f61dd089c",
        "keyword": "Arrijal",
        "tags": [],
        "weight": 1,
        "impressions": 1,
        "clicks": 0,
        "last_search": 1769353374702,
        "created_at": 1769353374702,
        "locale": "id"
      },
      {
        "id": "kw_07a78b49-67cb-4cbb-9037-c45c269c8702",
        "keyword": "ALUM",
        "tags": [],
        "weight": 1,
        "impressions": 1,
        "clicks": 0,
        "last_search": 1769353374702,
        "created_at": 1769353374702,
        "locale": "id"
      }
    ],
    "t": [
      {
        "id": "kw_e68bc785-4ae7-4993-9413-136702c2908e",
        "keyword": "Tutupe Wirang - Demy ...",
        "tags": [],
        "weight": 1,
        "impressions": 3,
        "clicks": 0,
        "last_search": 1769347436410,
        "created_at": 1769347230919,
        "locale": "id"
      }
    ],
    "h": [
      {
        "id": "kw_1d2d4a0d-32fb-4dfd-911f-8daf7cb7ee8f",
        "keyword": "Happy Asmara - Wirang ...",
        "tags": [],
        "weight": 1,
        "impressions": 3,
        "clicks": 0,
        "last_search": 1769347436410,
        "created_at": 1769347230919,
        "locale": "id"
      },
      {
        "id": "kw_9bfc6151-9dc5-4dba-880d-8b4ce7e0a062",
        "keyword": "Hendras Laros - Suruh Kemangi ...",
        "tags": [],
        "weight": 1,
        "impressions": 3,
        "clicks": 0,
        "last_search": 1769347436410,
        "created_at": 1769347230920,
        "locale": "id"
      }
    ],
    "n": [
      {
        "id": "kw_5954ccfa-6d7e-48b8-a58c-3f4f516d963d",
        "keyword": "Nadya Jessica - Semebyar ...",
        "tags": [],
        "weight": 1,
        "impressions": 3,
        "clicks": 0,
        "last_search": 1769347436410,
        "created_at": 1769347230919,
        "locale": "id"
      },
      {
        "id": "kw_d6cbb228-78b6-4ab0-8bae-2aee8d76e6db",
        "keyword": "Nanda Sari - Omah Suwung ...",
        "tags": [],
        "weight": 1,
        "impressions": 3,
        "clicks": 0,
        "last_search": 1769347436410,
        "created_at": 1769347230920,
        "locale": "id"
      },
      {
        "id": "kw_b78f6695-8e56-4a07-a419-f9bc7c137c87",
        "keyword": "NEMEN - GILDCOUSTIC",
        "tags": [],
        "weight": 1,
        "impressions": 1,
        "clicks": 0,
        "last_search": 1769353374701,
        "created_at": 1769353374701,
        "locale": "id"
      },
      {
        "id": "kw_0c279d53-8dd6-436e-8db0-84c2496e97ba",
        "keyword": "NEMEN",
        "tags": [],
        "weight": 1,
        "impressions": 1,
        "clicks": 0,
        "last_search": 1769353374701,
        "created_at": 1769353374701,
        "locale": "id"
      },
      {
        "id": "kw_0a903e83-2d21-46e4-9d3e-88303f371204",
        "keyword": "NEMEN - とんでもない (Japanese ...",
        "tags": [],
        "weight": 1,
        "impressions": 1,
        "clicks": 0,
        "last_search": 1769353374701,
        "created_at": 1769353374701,
        "locale": "id"
      },
      {
        "id": "kw_c484a061-b320-4fe7-9552-a87d832f882a",
        "keyword": "NDX AKA - Nemen HipHop Dangdut Version ...",
        "tags": [],
        "weight": 1,
        "impressions": 1,
        "clicks": 0,
        "last_search": 1769353374701,
        "created_at": 1769353374701,
        "locale": "id"
      },
      {
        "id": "kw_c70c50ca-f3c9-4849-84fc-a2c8fdc14e62",
        "keyword": "NDX AKA",
        "tags": [],
        "weight": 1,
        "impressions": 1,
        "clicks": 0,
        "last_search": 1769353374701,
        "created_at": 1769353374701,
        "locale": "id"
      },
      {
        "id": "kw_694f6069-bef3-4344-8e51-4b3500ea0a00",
        "keyword": "Nemen HipHop Dangdut Version ...",
        "tags": [],
        "weight": 1,
        "impressions": 1,
        "clicks": 0,
        "last_search": 1769353374701,
        "created_at": 1769353374701,
        "locale": "id"
      },
      {
        "id": "kw_03169155-bd80-426c-ba8e-1c2fb87cbe65",
        "keyword": "Nemen",
        "tags": [],
        "weight": 1,
        "impressions": 1,
        "clicks": 0,
        "last_search": 1769353374702,
        "created_at": 1769353374702,
        "locale": "id"
      },
      {
        "id": "kw_199e1cdc-0e69-49a9-b58f-68b309a52aa9",
        "keyword": "Nyeliwah",
        "tags": [],
        "weight": 1,
        "impressions": 1,
        "clicks": 0,
        "last_search": 1769353374702,
        "created_at": 1769353374702,
        "locale": "id"
      }
    ],
    "w": [
      {
        "id": "kw_59c64c7c-377a-4e37-af1b-21db6e1608b1",
        "keyword": "Watak - Alindra Musik",
        "tags": [],
        "weight": 1,
        "impressions": 3,
        "clicks": 0,
        "last_search": 1769347436410,
        "created_at": 1769347230919,
        "locale": "id"
      },
      {
        "id": "kw_ee83d76b-6c0f-4ddb-912f-d71aef4d9fd5",
        "keyword": "Wahyu F Giri - Lamunan",
        "tags": [],
        "weight": 1,
        "impressions": 2,
        "clicks": 0,
        "last_search": 1769349381266,
        "created_at": 1769348962016,
        "locale": "id"
      },
      {
        "id": "kw_8956e479-69a3-4b4e-9aef-b72a3a61bbf6",
        "keyword": "Wirang",
        "tags": [],
        "weight": 1,
        "impressions": 1,
        "clicks": 0,
        "last_search": 1769349381266,
        "created_at": 1769349381266,
        "locale": "id"
      },
      {
        "id": "kw_b66481fa-88e5-46de-a7f3-4d2a70c0f8fc",
        "keyword": "Wahyu F Giri",
        "tags": [],
        "weight": 1,
        "impressions": 1,
        "clicks": 0,
        "last_search": 1769349381266,
        "created_at": 1769349381266,
        "locale": "id"
      }
    ],
    "j": [
      {
        "id": "kw_24840a73-353d-4447-9f11-62c352f08f85",
        "keyword": "James AP - Kelangan Terakhir ...",
        "tags": [],
        "weight": 1,
        "impressions": 3,
        "clicks": 0,
        "last_search": 1769347436410,
        "created_at": 1769347230920,
        "locale": "id"
      }
    ],
    "l": [
      {
        "id": "kw_ad1b10de-c06c-4023-9713-3a8d09ac9502",
        "keyword": "Langgeng Dayaning Rasa (LDR ...",
        "tags": [],
        "weight": 1,
        "impressions": 1,
        "clicks": 0,
        "last_search": 1769349381265,
        "created_at": 1769349381265,
        "locale": "id"
      },
      {
        "id": "kw_c26ed07b-52ac-46a5-aab5-04f9b8f99097",
        "keyword": "Lamunan",
        "tags": [],
        "weight": 1,
        "impressions": 1,
        "clicks": 0,
        "last_search": 1769349381266,
        "created_at": 1769349381266,
        "locale": "id"
      },
      {
        "id": "kw_398cda6e-2c94-4682-88d7-a3a9181e310c",
        "keyword": "LAVORA Ft Ena Vika ...",
        "tags": [],
        "weight": 1,
        "impressions": 1,
        "clicks": 0,
        "last_search": 1769349381266,
        "created_at": 1769349381266,
        "locale": "id"
      }
    ],
    "g": [
      {
        "id": "kw_6a7dc2e6-3b8f-4fc0-8079-7abd790b0d68",
        "keyword": "GILDCOUSTIC",
        "tags": [],
        "weight": 1,
        "impressions": 1,
        "clicks": 0,
        "last_search": 1769353374701,
        "created_at": 1769353374701,
        "locale": "id"
      },
      {
        "id": "kw_eb5ae749-205c-4e40-a560-ffc247d5c961",
        "keyword": "GildCoustic - GINIO",
        "tags": [],
        "weight": 1,
        "impressions": 1,
        "clicks": 0,
        "last_search": 1769353374701,
        "created_at": 1769353374701,
        "locale": "id"
      },
      {
        "id": "kw_11cb2aa7-fdf9-4833-b7b2-6ff5ca8cdb62",
        "keyword": "GildCoustic",
        "tags": [],
        "weight": 1,
        "impressions": 1,
        "clicks": 0,
        "last_search": 1769353374701,
        "created_at": 1769353374701,
        "locale": "id"
      },
      {
        "id": "kw_52f5b999-47d9-4a27-8a04-9252cd10af94",
        "keyword": "GINIO",
        "tags": [],
        "weight": 1,
        "impressions": 1,
        "clicks": 0,
        "last_search": 1769353374702,
        "created_at": 1769353374701,
        "locale": "id"
      },
      {
        "id": "kw_830ce4af-6b76-42a8-adde-05bfe0647a08",
        "keyword": "GildCoustic - ALUM",
        "tags": [],
        "weight": 1,
        "impressions": 1,
        "clicks": 0,
        "last_search": 1769353374702,
        "created_at": 1769353374702,
        "locale": "id"
      }
    ],
    "f": [
      {
        "id": "kw_37fb8fc2-5399-48a9-9c13-567a98b6d226",
        "keyword": "Forysca & Saskia - NEMEN - とんでもない (Japanese ...",
        "tags": [],
        "weight": 1,
        "impressions": 1,
        "clicks": 0,
        "last_search": 1769353374701,
        "created_at": 1769353374701,
        "locale": "id"
      },
      {
        "id": "kw_31d9f930-118f-4295-be76-46de6618e1f2",
        "keyword": "Forysca & Saskia",
        "tags": [],
        "weight": 1,
        "impressions": 1,
        "clicks": 0,
        "last_search": 1769353374701,
        "created_at": 1769353374701,
        "locale": "id"
      },
      {
        "id": "kw_d474161e-f881-4671-99ec-fad049fa3c15",
        "keyword": "Fendi Loasana Ft Norsen Nenokeba - Cikirikici Cinta ...",
        "tags": [],
        "weight": 1,
        "impressions": 1,
        "clicks": 0,
        "last_search": 1769353374701,
        "created_at": 1769353374701,
        "locale": "id"
      },
      {
        "id": "kw_f0531f3a-0616-41c6-a75e-a4879aedd069",
        "keyword": "Fendi Loasana Ft Norsen Nenokeba",
        "tags": [],
        "weight": 1,
        "impressions": 1,
        "clicks": 0,
        "last_search": 1769353374701,
        "created_at": 1769353374701,
        "locale": "id"
      }
    ],
    "o": [
      {
        "id": "kw_af967a0a-7f32-40ac-9de3-c4816bfd8a42",
        "keyword": "Olivia Gunawan - Prei Sayang ...",
        "tags": [],
        "weight": 1,
        "impressions": 1,
        "clicks": 0,
        "last_search": 1769353374702,
        "created_at": 1769353374702,
        "locale": "id"
      },
      {
        "id": "kw_875547e9-0785-49f9-afef-9857d7093021",
        "keyword": "Olivia Gunawan",
        "tags": [],
        "weight": 1,
        "impressions": 1,
        "clicks": 0,
        "last_search": 1769353374702,
        "created_at": 1769353374702,
        "locale": "id"
      }
    ]
  }
}